discover_plugins.py
discover_plugins-0.1.7.dist-info/LICENSE
discover_plugins-0.1.7.dist-info/METADATA
discover_plugins-0.1.7.dist-info/WHEEL
discover_plugins-0.1.7.dist-info/entry_points.txt
discover_plugins-0.1.7.dist-info/top_level.txt
discover_plugins-0.1.7.dist-info/RECORD
