Metadata-Version: 2.1
Name: discover-plugins
Version: 0.1.7
Summary: Discover installed plugins
Author-email: Felix Scherz <felixwscherz@gmail.com>
License: MIT License
Project-URL: Documentation, https://github.com/felixscherz/discover-plugins#readme
Project-URL: Issues, https://github.com/felixscherz/discover-plugins/issues
Project-URL: Source, https://github.com/felixscherz/discover-plugins
Classifier: Programming Language :: Python
Classifier: Programming Language :: Python :: 3.10
Classifier: Programming Language :: Python :: 3.11
Classifier: Programming Language :: Python :: 3.12
Classifier: Programming Language :: Python :: Implementation :: CPython
Classifier: Programming Language :: Python :: Implementation :: PyPy
Requires-Python: >=3.10
License-File: LICENSE
